alonso/__init__.py
alonso/algorithm.py
alonso/app.py
alonso/applogger.py
alonso/batch.py
alonso/merge.py
alonso/parser.py
alonso/partition.py
alonso/stable.py
alonso/test.py
alonso/utils.py
alonso-0.1.0.dist-info/licenses/LICENSE
alonso-0.1.0.dist-info/METADATA
alonso-0.1.0.dist-info/WHEEL
alonso-0.1.0.dist-info/entry_points.txt
alonso-0.1.0.dist-info/top_level.txt
alonso-0.1.0.dist-info/RECORD
